jphrase/__init__.py
jphrase/phrase_splitter.py
jphrase-0.0.3.dist-info/LICENSE
jphrase-0.0.3.dist-info/METADATA
jphrase-0.0.3.dist-info/WHEEL
jphrase-0.0.3.dist-info/top_level.txt
jphrase-0.0.3.dist-info/RECORD
